[{"name":"name0","points":430,"toRecieveFreeCandy":0},{"name":"name1","points":407,"toRecieveFreeCandy":0},{"name":"name2","points":91,"toRecieveFreeCandy":0},{"name":"name3","points":480,"toRecieveFreeCandy":0},{"name":"name4","points":227,"toRecieveFreeCandy":0},{"name":"name5","points":130,"toRecieveFreeCandy":0},{"name":"name6","points":224,"toRecieveFreeCandy":0},{"name":"name7","points":302,"toRecieveFreeCandy":0},{"name":"name8","points":332,"toRecieveFreeCandy":0},{"name":"name9","points":120,"toRecieveFreeCandy":0},{"name":"name10","points":332,"toRecieveFreeCandy":0},{"name":"name11","points":453,"toRecieveFreeCandy":0},{"name":"name12","points":97,"toRecieveFreeCandy":0},{"name":"name13","points":340,"toRecieveFreeCandy":0},{"name":"name14","points":363,"toRecieveFreeCandy":0},{"name":"name15","points":225,"toRecieveFreeCandy":0},{"name":"name16","points":282,"toRecieveFreeCandy":0},{"name":"name17","points":469,"toRecieveFreeCandy":0},{"name":"name18","points":351,"toRecieveFreeCandy":0},{"name":"name19","points":398,"toRecieveFreeCandy":0},{"name":"name20","points":231,"toRecieveFreeCandy":0},{"name":"name21","points":292,"toRecieveFreeCandy":0},{"name":"name22","points":231,"toRecieveFreeCandy":0},{"name":"name23","points":492,"toRecieveFreeCandy":0},{"name":"name24","points":469,"toRecieveFreeCandy":0},{"name":"name25","points":484,"toRecieveFreeCandy":0},{"name":"name26","points":493,"toRecieveFreeCandy":0},{"name":"name27","points":215,"toRecieveFreeCandy":0},{"name":"name28","points":24,"toRecieveFreeCandy":0},{"name":"name29","points":44,"toRecieveFreeCandy":0},{"name":"name30","points":339,"toRecieveFreeCandy":0},{"name":"name31","points":361,"toRecieveFreeCandy":0},{"name":"name32","points":313,"toRecieveFreeCandy":0},{"name":"name33","points":331,"toRecieveFreeCandy":0},{"name":"name34","points":22,"toRecieveFreeCandy":0},{"name":"name35","points":132,"toRecieveFreeCandy":0},{"name":"name36","points":252,"toRecieveFreeCandy":0},{"name":"name37","points":271,"toRecieveFreeCandy":0},{"name":"name38","points":4,"toRecieveFreeCandy":0},{"name":"name39","points":201,"toRecieveFreeCandy":0},{"name":"name40","points":140,"toRecieveFreeCandy":0},{"name":"name41","points":191,"toRecieveFreeCandy":0},{"name":"name42","points":438,"toRecieveFreeCandy":0},{"name":"name43","points":459,"toRecieveFreeCandy":0},{"name":"name44","points":168,"toRecieveFreeCandy":0},{"name":"name45","points":193,"toRecieveFreeCandy":0},{"name":"name46","points":219,"toRecieveFreeCandy":0},{"name":"name47","points":454,"toRecieveFreeCandy":0},{"name":"name48","points":459,"toRecieveFreeCandy":0},{"name":"name49","points":337,"toRecieveFreeCandy":0},{"name":"name50","points":171,"toRecieveFreeCandy":0},{"name":"name51","points":77,"toRecieveFreeCandy":0},{"name":"name52","points":195,"toRecieveFreeCandy":0},{"name":"name53","points":329,"toRecieveFreeCandy":0},{"name":"name54","points":118,"toRecieveFreeCandy":0},{"name":"name55","points":345,"toRecieveFreeCandy":0},{"name":"name56","points":390,"toRecieveFreeCandy":0},{"name":"name57","points":497,"toRecieveFreeCandy":0},{"name":"name58","points":322,"toRecieveFreeCandy":0},{"name":"name59","points":331,"toRecieveFreeCandy":0},{"name":"name60","points":424,"toRecieveFreeCandy":0},{"name":"name61","points":430,"toRecieveFreeCandy":0},{"name":"name62","points":268,"toRecieveFreeCandy":0},{"name":"name63","points":140,"toRecieveFreeCandy":0},{"name":"name64","points":116,"toRecieveFreeCandy":0},{"name":"name65","points":107,"toRecieveFreeCandy":0},{"name":"name66","points":278,"toRecieveFreeCandy":0},{"name":"name67","points":402,"toRecieveFreeCandy":0},{"name":"name68","points":93,"toRecieveFreeCandy":0},{"name":"name69","points":378,"toRecieveFreeCandy":0},{"name":"name70","points":347,"toRecieveFreeCandy":0},{"name":"name71","points":295,"toRecieveFreeCandy":0},{"name":"name72","points":141,"toRecieveFreeCandy":0},{"name":"name73","points":54,"toRecieveFreeCandy":0},{"name":"name74","points":432,"toRecieveFreeCandy":0},{"name":"name75","points":477,"toRecieveFreeCandy":0},{"name":"name76","points":184,"toRecieveFreeCandy":0},{"name":"name77","points":309,"toRecieveFreeCandy":0},{"name":"name78","points":400,"toRecieveFreeCandy":0},{"name":"name79","points":276,"toRecieveFreeCandy":0},{"name":"name80","points":282,"toRecieveFreeCandy":0},{"name":"name81","points":220,"toRecieveFreeCandy":0},{"name":"name82","points":391,"toRecieveFreeCandy":0},{"name":"name83","points":337,"toRecieveFreeCandy":0},{"name":"name84","points":339,"toRecieveFreeCandy":0},{"name":"name85","points":82,"toRecieveFreeCandy":0},{"name":"name86","points":117,"toRecieveFreeCandy":0},{"name":"name87","points":247,"toRecieveFreeCandy":0},{"name":"name88","points":401,"toRecieveFreeCandy":0},{"name":"name89","points":288,"toRecieveFreeCandy":0},{"name":"name90","points":362,"toRecieveFreeCandy":0},{"name":"name91","points":177,"toRecieveFreeCandy":0},{"name":"name92","points":144,"toRecieveFreeCandy":0},{"name":"name93","points":146,"toRecieveFreeCandy":0},{"name":"name94","points":113,"toRecieveFreeCandy":0},{"name":"name95","points":280,"toRecieveFreeCandy":0},{"name":"name96","points":128,"toRecieveFreeCandy":0},{"name":"name97","points":494,"toRecieveFreeCandy":0},{"name":"name98","points":312,"toRecieveFreeCandy":0},{"name":"name99","points":59,"toRecieveFreeCandy":0},{"name":"name100","points":189,"toRecieveFreeCandy":0},{"name":"name101","points":71,"toRecieveFreeCandy":0},{"name":"name102","points":53,"toRecieveFreeCandy":0},{"name":"name103","points":132,"toRecieveFreeCandy":0},{"name":"name104","points":378,"toRecieveFreeCandy":0},{"name":"name105","points":451,"toRecieveFreeCandy":0},{"name":"name106","points":79,"toRecieveFreeCandy":0},{"name":"name107","points":238,"toRecieveFreeCandy":0},{"name":"name108","points":200,"toRecieveFreeCandy":0},{"name":"name109","points":102,"toRecieveFreeCandy":0},{"name":"name110","points":94,"toRecieveFreeCandy":0},{"name":"name111","points":398,"toRecieveFreeCandy":0},{"name":"name112","points":209,"toRecieveFreeCandy":0},{"name":"name113","points":179,"toRecieveFreeCandy":0},{"name":"name114","points":97,"toRecieveFreeCandy":0},{"name":"name115","points":328,"toRecieveFreeCandy":0},{"name":"name116","points":343,"toRecieveFreeCandy":0},{"name":"name117","points":333,"toRecieveFreeCandy":0},{"name":"name118","points":241,"toRecieveFreeCandy":0},{"name":"name119","points":434,"toRecieveFreeCandy":0},{"name":"name120","points":31,"toRecieveFreeCandy":0},{"name":"name121","points":253,"toRecieveFreeCandy":0},{"name":"name122","points":271,"toRecieveFreeCandy":0},{"name":"name123","points":352,"toRecieveFreeCandy":0},{"name":"name124","points":161,"toRecieveFreeCandy":0},{"name":"name125","points":35,"toRecieveFreeCandy":0},{"name":"name126","points":62,"toRecieveFreeCandy":0},{"name":"name127","points":343,"toRecieveFreeCandy":0},{"name":"name128","points":80,"toRecieveFreeCandy":0},{"name":"name129","points":358,"toRecieveFreeCandy":0},{"name":"name130","points":391,"toRecieveFreeCandy":0},{"name":"name131","points":187,"toRecieveFreeCandy":0},{"name":"name132","points":348,"toRecieveFreeCandy":0},{"name":"name133","points":102,"toRecieveFreeCandy":0},{"name":"name134","points":327,"toRecieveFreeCandy":0},{"name":"name135","points":404,"toRecieveFreeCandy":0},{"name":"name136","points":74,"toRecieveFreeCandy":0},{"name":"name137","points":404,"toRecieveFreeCandy":0},{"name":"name138","points":218,"toRecieveFreeCandy":0},{"name":"name139","points":34,"toRecieveFreeCandy":0},{"name":"name140","points":20,"toRecieveFreeCandy":0},{"name":"name141","points":33,"toRecieveFreeCandy":0},{"name":"name142","points":288,"toRecieveFreeCandy":0},{"name":"name143","points":345,"toRecieveFreeCandy":0},{"name":"name144","points":442,"toRecieveFreeCandy":0},{"name":"name145","points":159,"toRecieveFreeCandy":0},{"name":"name146","points":490,"toRecieveFreeCandy":0},{"name":"name147","points":336,"toRecieveFreeCandy":0},{"name":"name148","points":446,"toRecieveFreeCandy":0},{"name":"name149","points":235,"toRecieveFreeCandy":0},{"name":"name150","points":480,"toRecieveFreeCandy":0},{"name":"name151","points":297,"toRecieveFreeCandy":0},{"name":"name152","points":363,"toRecieveFreeCandy":0},{"name":"name153","points":278,"toRecieveFreeCandy":0},{"name":"name154","points":378,"toRecieveFreeCandy":0},{"name":"name155","points":463,"toRecieveFreeCandy":0},{"name":"name156","points":203,"toRecieveFreeCandy":0},{"name":"name157","points":29,"toRecieveFreeCandy":0},{"name":"name158","points":369,"toRecieveFreeCandy":0},{"name":"name159","points":319,"toRecieveFreeCandy":0},{"name":"name160","points":133,"toRecieveFreeCandy":0},{"name":"name161","points":400,"toRecieveFreeCandy":0},{"name":"name162","points":242,"toRecieveFreeCandy":0},{"name":"name163","points":57,"toRecieveFreeCandy":0},{"name":"name164","points":60,"toRecieveFreeCandy":0},{"name":"name165","points":97,"toRecieveFreeCandy":0},{"name":"name166","points":372,"toRecieveFreeCandy":0},{"name":"name167","points":393,"toRecieveFreeCandy":0},{"name":"name168","points":485,"toRecieveFreeCandy":0},{"name":"name169","points":210,"toRecieveFreeCandy":0},{"name":"name170","points":234,"toRecieveFreeCandy":0},{"name":"name171","points":325,"toRecieveFreeCandy":0},{"name":"name172","points":138,"toRecieveFreeCandy":0},{"name":"name173","points":147,"toRecieveFreeCandy":0},{"name":"name174","points":125,"toRecieveFreeCandy":0},{"name":"name175","points":243,"toRecieveFreeCandy":0},{"name":"name176","points":100,"toRecieveFreeCandy":0},{"name":"name177","points":130,"toRecieveFreeCandy":0},{"name":"name178","points":416,"toRecieveFreeCandy":0},{"name":"name179","points":139,"toRecieveFreeCandy":0},{"name":"name180","points":38,"toRecieveFreeCandy":0},{"name":"name181","points":482,"toRecieveFreeCandy":0},{"name":"name182","points":1,"toRecieveFreeCandy":0},{"name":"name183","points":69,"toRecieveFreeCandy":0},{"name":"name184","points":405,"toRecieveFreeCandy":0},{"name":"name185","points":84,"toRecieveFreeCandy":0},{"name":"name186","points":7,"toRecieveFreeCandy":0},{"name":"name187","points":337,"toRecieveFreeCandy":0},{"name":"name188","points":255,"toRecieveFreeCandy":0},{"name":"name189","points":108,"toRecieveFreeCandy":0},{"name":"name190","points":84,"toRecieveFreeCandy":0},{"name":"name191","points":4,"toRecieveFreeCandy":0},{"name":"name192","points":331,"toRecieveFreeCandy":0},{"name":"name193","points":127,"toRecieveFreeCandy":0},{"name":"name194","points":282,"toRecieveFreeCandy":0},{"name":"name195","points":265,"toRecieveFreeCandy":0},{"name":"name196","points":261,"toRecieveFreeCandy":0},{"name":"name197","points":252,"toRecieveFreeCandy":0},{"name":"name198","points":493,"toRecieveFreeCandy":0},{"name":"name199","points":122,"toRecieveFreeCandy":0},{"name":"name200","points":162,"toRecieveFreeCandy":0},{"name":"name201","points":60,"toRecieveFreeCandy":0},{"name":"name202","points":99,"toRecieveFreeCandy":0},{"name":"name203","points":22,"toRecieveFreeCandy":0},{"name":"name204","points":178,"toRecieveFreeCandy":0},{"name":"name205","points":434,"toRecieveFreeCandy":0},{"name":"name206","points":450,"toRecieveFreeCandy":0},{"name":"name207","points":14,"toRecieveFreeCandy":0},{"name":"name208","points":211,"toRecieveFreeCandy":0},{"name":"name209","points":117,"toRecieveFreeCandy":0},{"name":"name210","points":123,"toRecieveFreeCandy":0},{"name":"name211","points":250,"toRecieveFreeCandy":0},{"name":"name212","points":497,"toRecieveFreeCandy":0},{"name":"name213","points":415,"toRecieveFreeCandy":0},{"name":"name214","points":388,"toRecieveFreeCandy":0},{"name":"name215","points":275,"toRecieveFreeCandy":0},{"name":"name216","points":330,"toRecieveFreeCandy":0},{"name":"name217","points":326,"toRecieveFreeCandy":0},{"name":"name218","points":110,"toRecieveFreeCandy":0},{"name":"name219","points":111,"toRecieveFreeCandy":0},{"name":"name220","points":161,"toRecieveFreeCandy":0},{"name":"name221","points":403,"toRecieveFreeCandy":0},{"name":"name222","points":44,"toRecieveFreeCandy":0},{"name":"name223","points":448,"toRecieveFreeCandy":0},{"name":"name224","points":415,"toRecieveFreeCandy":0},{"name":"name225","points":103,"toRecieveFreeCandy":0},{"name":"name226","points":426,"toRecieveFreeCandy":0},{"name":"name227","points":136,"toRecieveFreeCandy":0},{"name":"name228","points":333,"toRecieveFreeCandy":0},{"name":"name229","points":26,"toRecieveFreeCandy":0},{"name":"name230","points":282,"toRecieveFreeCandy":0},{"name":"name231","points":252,"toRecieveFreeCandy":0},{"name":"name232","points":1,"toRecieveFreeCandy":0},{"name":"name233","points":414,"toRecieveFreeCandy":0},{"name":"name234","points":160,"toRecieveFreeCandy":0},{"name":"name235","points":314,"toRecieveFreeCandy":0},{"name":"name236","points":11,"toRecieveFreeCandy":0},{"name":"name237","points":390,"toRecieveFreeCandy":0},{"name":"name238","points":332,"toRecieveFreeCandy":0},{"name":"name239","points":68,"toRecieveFreeCandy":0},{"name":"name240","points":54,"toRecieveFreeCandy":0},{"name":"name241","points":247,"toRecieveFreeCandy":0},{"name":"name242","points":36,"toRecieveFreeCandy":0},{"name":"name243","points":235,"toRecieveFreeCandy":0},{"name":"name244","points":487,"toRecieveFreeCandy":0},{"name":"name245","points":372,"toRecieveFreeCandy":0},{"name":"name246","points":455,"toRecieveFreeCandy":0},{"name":"name247","points":211,"toRecieveFreeCandy":0},{"name":"name248","points":337,"toRecieveFreeCandy":0},{"name":"name249","points":340,"toRecieveFreeCandy":0},{"name":"name250","points":238,"toRecieveFreeCandy":0},{"name":"name251","points":324,"toRecieveFreeCandy":0},{"name":"name252","points":255,"toRecieveFreeCandy":0},{"name":"name253","points":51,"toRecieveFreeCandy":0},{"name":"name254","points":109,"toRecieveFreeCandy":0},{"name":"name255","points":399,"toRecieveFreeCandy":0},{"name":"name256","points":286,"toRecieveFreeCandy":0},{"name":"name257","points":177,"toRecieveFreeCandy":0},{"name":"name258","points":382,"toRecieveFreeCandy":0},{"name":"name259","points":311,"toRecieveFreeCandy":0},{"name":"name260","points":126,"toRecieveFreeCandy":0},{"name":"name261","points":407,"toRecieveFreeCandy":0},{"name":"name262","points":35,"toRecieveFreeCandy":0},{"name":"name263","points":303,"toRecieveFreeCandy":0},{"name":"name264","points":239,"toRecieveFreeCandy":0},{"name":"name265","points":15,"toRecieveFreeCandy":0},{"name":"name266","points":266,"toRecieveFreeCandy":0},{"name":"name267","points":429,"toRecieveFreeCandy":0},{"name":"name268","points":434,"toRecieveFreeCandy":0},{"name":"name269","points":184,"toRecieveFreeCandy":0},{"name":"name270","points":162,"toRecieveFreeCandy":0},{"name":"name271","points":223,"toRecieveFreeCandy":0},{"name":"name272","points":122,"toRecieveFreeCandy":0},{"name":"name273","points":217,"toRecieveFreeCandy":0},{"name":"name274","points":24,"toRecieveFreeCandy":0},{"name":"name275","points":165,"toRecieveFreeCandy":0},{"name":"name276","points":0,"toRecieveFreeCandy":0},{"name":"name277","points":168,"toRecieveFreeCandy":0},{"name":"name278","points":175,"toRecieveFreeCandy":0},{"name":"name279","points":122,"toRecieveFreeCandy":0},{"name":"name280","points":137,"toRecieveFreeCandy":0},{"name":"name281","points":54,"toRecieveFreeCandy":0},{"name":"name282","points":310,"toRecieveFreeCandy":0},{"name":"name283","points":239,"toRecieveFreeCandy":0},{"name":"name284","points":67,"toRecieveFreeCandy":0},{"name":"name285","points":293,"toRecieveFreeCandy":0},{"name":"name286","points":159,"toRecieveFreeCandy":0},{"name":"name287","points":233,"toRecieveFreeCandy":0},{"name":"name288","points":329,"toRecieveFreeCandy":0},{"name":"name289","points":8,"toRecieveFreeCandy":0},{"name":"name290","points":121,"toRecieveFreeCandy":0},{"name":"name291","points":62,"toRecieveFreeCandy":0},{"name":"name292","points":383,"toRecieveFreeCandy":0},{"name":"name293","points":467,"toRecieveFreeCandy":0},{"name":"name294","points":146,"toRecieveFreeCandy":0},{"name":"name295","points":384,"toRecieveFreeCandy":0},{"name":"name296","points":420,"toRecieveFreeCandy":0},{"name":"name297","points":380,"toRecieveFreeCandy":0},{"name":"name298","points":347,"toRecieveFreeCandy":0},{"name":"name299","points":310,"toRecieveFreeCandy":0},{"name":"name300","points":39,"toRecieveFreeCandy":0},{"name":"name301","points":490,"toRecieveFreeCandy":0},{"name":"name302","points":91,"toRecieveFreeCandy":0},{"name":"name303","points":46,"toRecieveFreeCandy":0},{"name":"name304","points":445,"toRecieveFreeCandy":0},{"name":"name305","points":56,"toRecieveFreeCandy":0},{"name":"name306","points":139,"toRecieveFreeCandy":0},{"name":"name307","points":253,"toRecieveFreeCandy":0},{"name":"name308","points":331,"toRecieveFreeCandy":0},{"name":"name309","points":346,"toRecieveFreeCandy":0},{"name":"name310","points":311,"toRecieveFreeCandy":0},{"name":"name311","points":251,"toRecieveFreeCandy":0},{"name":"name312","points":497,"toRecieveFreeCandy":0},{"name":"name313","points":435,"toRecieveFreeCandy":0},{"name":"name314","points":28,"toRecieveFreeCandy":0},{"name":"name315","points":168,"toRecieveFreeCandy":0},{"name":"name316","points":141,"toRecieveFreeCandy":0},{"name":"name317","points":12,"toRecieveFreeCandy":0},{"name":"name318","points":243,"toRecieveFreeCandy":0},{"name":"name319","points":60,"toRecieveFreeCandy":0},{"name":"name320","points":485,"toRecieveFreeCandy":0},{"name":"name321","points":429,"toRecieveFreeCandy":0},{"name":"name322","points":318,"toRecieveFreeCandy":0},{"name":"name323","points":370,"toRecieveFreeCandy":0},{"name":"name324","points":281,"toRecieveFreeCandy":0},{"name":"name325","points":206,"toRecieveFreeCandy":0},{"name":"name326","points":443,"toRecieveFreeCandy":0},{"name":"name327","points":354,"toRecieveFreeCandy":0},{"name":"name328","points":294,"toRecieveFreeCandy":0},{"name":"name329","points":375,"toRecieveFreeCandy":0},{"name":"name330","points":388,"toRecieveFreeCandy":0},{"name":"name331","points":489,"toRecieveFreeCandy":0},{"name":"name332","points":188,"toRecieveFreeCandy":0},{"name":"name333","points":155,"toRecieveFreeCandy":0},{"name":"name334","points":28,"toRecieveFreeCandy":0},{"name":"name335","points":181,"toRecieveFreeCandy":0},{"name":"name336","points":333,"toRecieveFreeCandy":0},{"name":"name337","points":107,"toRecieveFreeCandy":0},{"name":"name338","points":32,"toRecieveFreeCandy":0},{"name":"name339","points":318,"toRecieveFreeCandy":0},{"name":"name340","points":0,"toRecieveFreeCandy":0},{"name":"name341","points":301,"toRecieveFreeCandy":0},{"name":"name342","points":481,"toRecieveFreeCandy":0},{"name":"name343","points":282,"toRecieveFreeCandy":0},{"name":"name344","points":50,"toRecieveFreeCandy":0},{"name":"name345","points":496,"toRecieveFreeCandy":0},{"name":"name346","points":84,"toRecieveFreeCandy":0},{"name":"name347","points":115,"toRecieveFreeCandy":0},{"name":"name348","points":63,"toRecieveFreeCandy":0},{"name":"name349","points":360,"toRecieveFreeCandy":0},{"name":"name350","points":339,"toRecieveFreeCandy":0},{"name":"name351","points":176,"toRecieveFreeCandy":0},{"name":"name352","points":449,"toRecieveFreeCandy":0},{"name":"name353","points":24,"toRecieveFreeCandy":0},{"name":"name354","points":89,"toRecieveFreeCandy":0},{"name":"name355","points":357,"toRecieveFreeCandy":0},{"name":"name356","points":174,"toRecieveFreeCandy":0},{"name":"name357","points":175,"toRecieveFreeCandy":0},{"name":"name358","points":437,"toRecieveFreeCandy":0},{"name":"name359","points":67,"toRecieveFreeCandy":0},{"name":"name360","points":308,"toRecieveFreeCandy":0},{"name":"name361","points":29,"toRecieveFreeCandy":0},{"name":"name362","points":464,"toRecieveFreeCandy":0},{"name":"name363","points":238,"toRecieveFreeCandy":0},{"name":"name364","points":398,"toRecieveFreeCandy":0},{"name":"name365","points":112,"toRecieveFreeCandy":0},{"name":"name366","points":345,"toRecieveFreeCandy":0},{"name":"name367","points":372,"toRecieveFreeCandy":0},{"name":"name368","points":147,"toRecieveFreeCandy":0},{"name":"name369","points":389,"toRecieveFreeCandy":0},{"name":"name370","points":234,"toRecieveFreeCandy":0},{"name":"name371","points":108,"toRecieveFreeCandy":0},{"name":"name372","points":213,"toRecieveFreeCandy":0},{"name":"name373","points":95,"toRecieveFreeCandy":0},{"name":"name374","points":241,"toRecieveFreeCandy":0},{"name":"name375","points":334,"toRecieveFreeCandy":0},{"name":"name376","points":370,"toRecieveFreeCandy":0},{"name":"name377","points":174,"toRecieveFreeCandy":0},{"name":"name378","points":54,"toRecieveFreeCandy":0},{"name":"name379","points":188,"toRecieveFreeCandy":0},{"name":"name380","points":262,"toRecieveFreeCandy":0},{"name":"name381","points":320,"toRecieveFreeCandy":0},{"name":"name382","points":220,"toRecieveFreeCandy":0},{"name":"name383","points":287,"toRecieveFreeCandy":0},{"name":"name384","points":455,"toRecieveFreeCandy":0},{"name":"name385","points":85,"toRecieveFreeCandy":0},{"name":"name386","points":26,"toRecieveFreeCandy":0},{"name":"name387","points":25,"toRecieveFreeCandy":0},{"name":"name388","points":37,"toRecieveFreeCandy":0},{"name":"name389","points":358,"toRecieveFreeCandy":0},{"name":"name390","points":315,"toRecieveFreeCandy":0},{"name":"name391","points":165,"toRecieveFreeCandy":0},{"name":"name392","points":100,"toRecieveFreeCandy":0},{"name":"name393","points":279,"toRecieveFreeCandy":0},{"name":"name394","points":404,"toRecieveFreeCandy":0},{"name":"name395","points":284,"toRecieveFreeCandy":0},{"name":"name396","points":51,"toRecieveFreeCandy":0},{"name":"name397","points":256,"toRecieveFreeCandy":0},{"name":"name398","points":226,"toRecieveFreeCandy":0},{"name":"name399","points":242,"toRecieveFreeCandy":0},{"name":"name400","points":364,"toRecieveFreeCandy":0},{"name":"name401","points":481,"toRecieveFreeCandy":0},{"name":"name402","points":471,"toRecieveFreeCandy":0},{"name":"name403","points":105,"toRecieveFreeCandy":0},{"name":"name404","points":451,"toRecieveFreeCandy":0},{"name":"name405","points":361,"toRecieveFreeCandy":0},{"name":"name406","points":72,"toRecieveFreeCandy":0},{"name":"name407","points":30,"toRecieveFreeCandy":0},{"name":"name408","points":418,"toRecieveFreeCandy":0},{"name":"name409","points":243,"toRecieveFreeCandy":0},{"name":"name410","points":470,"toRecieveFreeCandy":0},{"name":"name411","points":37,"toRecieveFreeCandy":0},{"name":"name412","points":266,"toRecieveFreeCandy":0},{"name":"name413","points":167,"toRecieveFreeCandy":0},{"name":"name414","points":482,"toRecieveFreeCandy":0},{"name":"name415","points":299,"toRecieveFreeCandy":0},{"name":"name416","points":125,"toRecieveFreeCandy":0},{"name":"name417","points":144,"toRecieveFreeCandy":0},{"name":"name418","points":12,"toRecieveFreeCandy":0},{"name":"name419","points":98,"toRecieveFreeCandy":0},{"name":"name420","points":138,"toRecieveFreeCandy":0},{"name":"name421","points":458,"toRecieveFreeCandy":0},{"name":"name422","points":46,"toRecieveFreeCandy":0},{"name":"name423","points":250,"toRecieveFreeCandy":0},{"name":"name424","points":454,"toRecieveFreeCandy":0},{"name":"name425","points":150,"toRecieveFreeCandy":0},{"name":"name426","points":48,"toRecieveFreeCandy":0},{"name":"name427","points":455,"toRecieveFreeCandy":0},{"name":"name428","points":431,"toRecieveFreeCandy":0},{"name":"name429","points":142,"toRecieveFreeCandy":0},{"name":"name430","points":267,"toRecieveFreeCandy":0},{"name":"name431","points":207,"toRecieveFreeCandy":0},{"name":"name432","points":427,"toRecieveFreeCandy":0},{"name":"name433","points":363,"toRecieveFreeCandy":0},{"name":"name434","points":154,"toRecieveFreeCandy":0},{"name":"name435","points":371,"toRecieveFreeCandy":0},{"name":"name436","points":100,"toRecieveFreeCandy":0},{"name":"name437","points":414,"toRecieveFreeCandy":0},{"name":"name438","points":277,"toRecieveFreeCandy":0},{"name":"name439","points":12,"toRecieveFreeCandy":0},{"name":"name440","points":285,"toRecieveFreeCandy":0},{"name":"name441","points":376,"toRecieveFreeCandy":0},{"name":"name442","points":55,"toRecieveFreeCandy":0},{"name":"name443","points":381,"toRecieveFreeCandy":0},{"name":"name444","points":278,"toRecieveFreeCandy":0},{"name":"name445","points":487,"toRecieveFreeCandy":0},{"name":"name446","points":461,"toRecieveFreeCandy":0},{"name":"name447","points":498,"toRecieveFreeCandy":0},{"name":"name448","points":303,"toRecieveFreeCandy":0},{"name":"name449","points":248,"toRecieveFreeCandy":0},{"name":"name450","points":112,"toRecieveFreeCandy":0},{"name":"name451","points":198,"toRecieveFreeCandy":0},{"name":"name452","points":77,"toRecieveFreeCandy":0},{"name":"name453","points":112,"toRecieveFreeCandy":0},{"name":"name454","points":272,"toRecieveFreeCandy":0},{"name":"name455","points":281,"toRecieveFreeCandy":0},{"name":"name456","points":217,"toRecieveFreeCandy":0},{"name":"name457","points":25,"toRecieveFreeCandy":0},{"name":"name458","points":393,"toRecieveFreeCandy":0},{"name":"name459","points":284,"toRecieveFreeCandy":0},{"name":"name460","points":312,"toRecieveFreeCandy":0},{"name":"name461","points":463,"toRecieveFreeCandy":0},{"name":"name462","points":163,"toRecieveFreeCandy":0},{"name":"name463","points":172,"toRecieveFreeCandy":0},{"name":"name464","points":76,"toRecieveFreeCandy":0},{"name":"name465","points":492,"toRecieveFreeCandy":0},{"name":"name466","points":97,"toRecieveFreeCandy":0},{"name":"name467","points":58,"toRecieveFreeCandy":0},{"name":"name468","points":288,"toRecieveFreeCandy":0},{"name":"name469","points":14,"toRecieveFreeCandy":0},{"name":"name470","points":247,"toRecieveFreeCandy":0},{"name":"name471","points":264,"toRecieveFreeCandy":0},{"name":"name472","points":280,"toRecieveFreeCandy":0},{"name":"name473","points":250,"toRecieveFreeCandy":0},{"name":"name474","points":86,"toRecieveFreeCandy":0},{"name":"name475","points":396,"toRecieveFreeCandy":0},{"name":"name476","points":155,"toRecieveFreeCandy":0},{"name":"name477","points":285,"toRecieveFreeCandy":0},{"name":"name478","points":263,"toRecieveFreeCandy":0},{"name":"name479","points":247,"toRecieveFreeCandy":0},{"name":"name480","points":112,"toRecieveFreeCandy":0},{"name":"name481","points":266,"toRecieveFreeCandy":0},{"name":"name482","points":164,"toRecieveFreeCandy":0},{"name":"name483","points":143,"toRecieveFreeCandy":0},{"name":"name484","points":153,"toRecieveFreeCandy":0},{"name":"name485","points":44,"toRecieveFreeCandy":0},{"name":"name486","points":207,"toRecieveFreeCandy":0},{"name":"name487","points":392,"toRecieveFreeCandy":0},{"name":"name488","points":338,"toRecieveFreeCandy":0},{"name":"name489","points":279,"toRecieveFreeCandy":0},{"name":"name490","points":452,"toRecieveFreeCandy":0},{"name":"name491","points":340,"toRecieveFreeCandy":0},{"name":"name492","points":222,"toRecieveFreeCandy":0},{"name":"name493","points":221,"toRecieveFreeCandy":0},{"name":"name494","points":293,"toRecieveFreeCandy":0},{"name":"name495","points":173,"toRecieveFreeCandy":0},{"name":"name496","points":18,"toRecieveFreeCandy":0},{"name":"name497","points":4,"toRecieveFreeCandy":0},{"name":"name498","points":109,"toRecieveFreeCandy":0},{"name":"name499","points":189,"toRecieveFreeCandy":0}]